prelude_parser-0.15.0.dist-info/METADATA
prelude_parser-0.15.0.dist-info/WHEEL
prelude_parser-0.15.0.dist-info/licenses/LICENSE
prelude_parser/__init__.py
prelude_parser/_prelude_parser.cpython-312-arm-linux-gnueabihf.so
prelude_parser/_prelude_parser.pyi
prelude_parser/pandas.py
prelude_parser/parser.py
prelude_parser/polars.py
prelude_parser/py.typed
prelude_parser/types.py
prelude_parser-0.15.0.dist-info/RECORD
