Metadata-Version: 2.4
Name: prelude-parser
Version: 0.15.0
Classifier: Programming Language :: Rust
Classifier: Programming Language :: Python :: Implementation :: CPython
Classifier: Programming Language :: Python :: 3.10
Classifier: Programming Language :: Python :: 3.11
Classifier: Programming Language :: Python :: 3.12
Classifier: Programming Language :: Python :: 3.13
Classifier: Programming Language :: Python :: 3.14
Classifier: Programming Language :: Rust
Classifier: License :: OSI Approved :: MIT License
Classifier: Typing :: Typed
Requires-Dist: camel-converter>=3.0.0
Requires-Dist: pandas>=2.1.0 ; extra == 'pandas'
Requires-Dist: polars>=0.17.14 ; extra == 'polars'
Requires-Dist: pandas>=2.1.0 ; extra == 'all'
Requires-Dist: polars>=0.17.14 ; extra == 'all'
Provides-Extra: pandas
Provides-Extra: polars
Provides-Extra: all
License-File: LICENSE
Summary: Parses XML files exported from Prelude EDC into formats usable by Python.
Keywords: parser,prelude-edc,xml,pandas,polars
Home-Page: https://github.com/pbs-data-solutions/prelude-parser
Author-email: Paul Sanders <paul@pbsdatasolutions.com>
Requires-Python: >=3.10
